[{"pk": 406678484, "username": "imdb", "full_name": "IMDb", "is_private": false, "profile_pic_url": "https://scontent-tpe1-1.cdninstagram.com/v/t51.2885-19/s150x150/57390247_440185083471396_4330954311577108480_n.jpg?_nc_ht=scontent-tpe1-1.cdninstagram.com&_nc_ohc=8v5Lr4klZLcAX_TGuZA&oh=cc82e2fe51e4366d9c9c5df88b587d78&oe=5E9E8B7C", "profile_pic_id": "2035782135224031478_406678484", "is_verified": true, "has_anonymous_profile_picture": false, "can_see_primary_country_in_settings": false, "latest_reel_media": 1578291259, "is_favorite": false}, {"pk": 12790471130, "username": "kentai_wifi", "full_name": "\u30db\u30fc\u30ad\u30f3\u30b9\u5148\u8f29\ud83d\udc09\ud83d\udcf6", "is_private": false, "profile_pic_url": "https://scontent-tpe1-1.cdninstagram.com/v/t51.2885-19/s150x150/79532302_1035542406779731_8351125897717219328_n.jpg?_nc_ht=scontent-tpe1-1.cdninstagram.com&_nc_ohc=W4od9IXJdhYAX_1_m_V&oh=b3e2e779c7d64d0cd1c92880e6f3164e&oe=5E993434", "profile_pic_id": "2215038006042460919_12790471130", "is_verified": false, "has_anonymous_profile_picture": false, "can_see_primary_country_in_settings": false, "latest_reel_media": 1578284733, "is_favorite": false}, {"pk": 9252890760, "username": "justdec", "full_name": "Justin Dec", "is_private": false, "profile_pic_url": "https://scontent-tpe1-1.cdninstagram.com/v/t51.2885-19/s150x150/68760153_2395736387361811_5691319627024433152_n.jpg?_nc_ht=scontent-tpe1-1.cdninstagram.com&_nc_ohc=ZtOfgkX-_lgAX9BEDOq&oh=9940fb80db36d93132d9b85faf3bd7b3&oe=5E8D4B1C", "profile_pic_id": "2117723582412320802_9252890760", "is_verified": false, "has_anonymous_profile_picture": false, "can_see_primary_country_in_settings": false, "latest_reel_media": 0, "is_favorite": false}, {"pk": 6033801, "username": "dukegonzo", "full_name": "Dillon Lane", "is_private": false, "profile_pic_url": "https://scontent-tpe1-1.cdninstagram.com/v/t51.2885-19/s150x150/71897040_573150253427276_2795522371048439808_n.jpg?_nc_ht=scontent-tpe1-1.cdninstagram.com&_nc_ohc=y-MAtMABrpEAX-0JCeI&oh=f7cccd98456637d6093acd6a088fb005&oe=5EA8EBEB", "profile_pic_id": "2162627133101817150_6033801", "is_verified": false, "has_anonymous_profile_picture": false, "can_see_primary_country_in_settings": false, "latest_reel_media": 1578251153, "is_favorite": false}, {"pk": 25033690, "username": "elizabethlail", "full_name": "Elizabeth Dean Lail", "is_private": false, "profile_pic_url": "https://scontent-tpe1-1.cdninstagram.com/v/t51.2885-19/s150x150/78715281_2785979024795151_8763119252606550016_n.jpg?_nc_ht=scontent-tpe1-1.cdninstagram.com&_nc_ohc=KzPUwE8r8moAX92dFcK&oh=5f0a108cb7ce057d42e97b81bb45ac0f&oe=5EA2D3AF", "profile_pic_id": "2203443074177544372_25033690", "is_verified": true, "has_anonymous_profile_picture": false, "can_see_primary_country_in_settings": false, "latest_reel_media": 0, "is_favorite": false}, {"pk": 11338527, "username": "pj_byrne", "full_name": "PJ Byrne", "is_private": false, "profile_pic_url": "https://scontent-tpe1-1.cdninstagram.com/v/t51.2885-19/11264609_931150483615375_561708487_a.jpg?_nc_ht=scontent-tpe1-1.cdninstagram.com&_nc_ohc=M1y9PM2p5n4AX8mhXqJ&oh=e4460e23d3b4e4526f41fd6dbb7ce207&oe=5E943B5C", "is_verified": true, "has_anonymous_profile_picture": false, "can_see_primary_country_in_settings": false, "latest_reel_media": 1578292450, "is_favorite": false}, {"pk": 21767027, "username": "peterfacinelli", "full_name": "Peter Facinelli", "is_private": false, "profile_pic_url": "https://scontent-tpe1-1.cdninstagram.com/v/t51.2885-19/s150x150/18949662_1733297596969222_9068196947214467072_a.jpg?_nc_ht=scontent-tpe1-1.cdninstagram.com&_nc_ohc=yeRmIHB56kMAX-NueCX&oh=e7d477302793d6d8f995966ff18ca6a1&oe=5E9DD177", "profile_pic_id": "1534527938154610338_21767027", "is_verified": true, "has_anonymous_profile_picture": false, "can_see_primary_country_in_settings": false, "latest_reel_media": 0, "is_favorite": false}, {"pk": 1295950186, "username": "benazelart", "full_name": "Ben Azelart", "is_private": false, "profile_pic_url": "https://scontent-tpe1-1.cdninstagram.com/v/t51.2885-19/s150x150/75408721_1628130780661883_3654319949674971136_n.jpg?_nc_ht=scontent-tpe1-1.cdninstagram.com&_nc_ohc=pI10oepfHlcAX8XdA2J&oh=d1c7f1b5e49ed98cbd353c064ca3de77&oe=5E8D8370", "profile_pic_id": "2200409358765340374_1295950186", "is_verified": true, "has_anonymous_profile_picture": false, "can_see_primary_country_in_settings": false, "latest_reel_media": 1578260994, "is_favorite": false}, {"pk": 39650211, "username": "brentrivera", "full_name": "Brent Rivera", "is_private": false, "profile_pic_url": "https://scontent-tpe1-1.cdninstagram.com/v/t51.2885-19/s150x150/50224254_297470897637640_7011830630967148544_n.jpg?_nc_ht=scontent-tpe1-1.cdninstagram.com&_nc_ohc=tIPwSKpjQkIAX9F8-rp&oh=52ed389f560b51d3292d614fbbf620ac&oe=5EB40422", "profile_pic_id": "1967287821016029524_39650211", "is_verified": true, "has_anonymous_profile_picture": false, "can_see_primary_country_in_settings": false, "latest_reel_media": 1578264396, "is_favorite": false}, {"pk": 174662198, "username": "lexibrookerivera", "full_name": "Lexi Rivera", "is_private": false, "profile_pic_url": "https://scontent-tpe1-1.cdninstagram.com/v/t51.2885-19/s150x150/50981699_2074341499315187_2952075505240637440_n.jpg?_nc_ht=scontent-tpe1-1.cdninstagram.com&_nc_ohc=XNBGv6sNV40AX8H8ItN&oh=8e8618128a362cdc64e5e531d79a5a50&oe=5EAE720E", "profile_pic_id": "1978117047654546235_174662198", "is_verified": true, "has_anonymous_profile_picture": false, "can_see_primary_country_in_settings": false, "latest_reel_media": 1578276635, "is_favorite": false}, {"pk": 578105687, "username": "ttbate", "full_name": "\u2666\ufe0fTalitha Eliana Bateman", "is_private": false, "profile_pic_url": "https://scontent-tpe1-1.cdninstagram.com/v/t51.2885-19/s150x150/76962303_571099103624390_5082032654426046464_n.jpg?_nc_ht=scontent-tpe1-1.cdninstagram.com&_nc_ohc=jxcmXP4xRk4AX-hdadC&oh=e31eb030f0faf455fb6e8c2957400466&oe=5EACF70A", "profile_pic_id": "2200402962358383368_578105687", "is_verified": true, "has_anonymous_profile_picture": false, "can_see_primary_country_in_settings": false, "latest_reel_media": 1578271764, "is_favorite": false}, {"pk": 22680409, "username": "seguratom", "full_name": "Tom Segura", "is_private": false, "profile_pic_url": "https://scontent-tpe1-1.cdninstagram.com/v/t51.2885-19/s150x150/41266541_787223341608683_3926907316200275968_n.jpg?_nc_ht=scontent-tpe1-1.cdninstagram.com&_nc_ohc=GlITYfIrHEwAX-g0Pmo&oh=7dae3a834e7c6ceb3d2dd13e58f76017&oe=5E988DA5", "profile_pic_id": "1873437478780010613_22680409", "is_verified": true, "has_anonymous_profile_picture": false, "can_see_primary_country_in_settings": false, "latest_reel_media": 1578270303, "is_favorite": false}, {"pk": 13486861, "username": "jeannieelisemai", "full_name": "\ud83d\udc8e", "is_private": false, "profile_pic_url": "https://scontent-tpe1-1.cdninstagram.com/v/t51.2885-19/s150x150/66967669_387099368676628_3373434117923274752_n.jpg?_nc_ht=scontent-tpe1-1.cdninstagram.com&_nc_ohc=8Df0crwzPCEAX-Itbz1&oh=02d51063fc907ab6839cf939306cd018&oe=5EA29F6A", "profile_pic_id": "2114279999864073122_13486861", "is_verified": false, "has_anonymous_profile_picture": false, "can_see_primary_country_in_settings": false, "latest_reel_media": 1578279720, "is_favorite": false}, {"pk": 43184707, "username": "annewinters", "full_name": "Lil Anne \ud83d\udc8b\ud83c\udf52", "is_private": false, "profile_pic_url": "https://scontent-tpe1-1.cdninstagram.com/v/t51.2885-19/s150x150/78985800_423445855202257_1253218654644862976_n.jpg?_nc_ht=scontent-tpe1-1.cdninstagram.com&_nc_ohc=5M_-ZMW-UTAAX_aCY4i&oh=ec2aae67a6bef08d9e3003c24df4fa49&oe=5EA4611F", "profile_pic_id": "2194508165763383908_43184707", "is_verified": true, "has_anonymous_profile_picture": false, "can_see_primary_country_in_settings": false, "latest_reel_media": 1578282042, "is_favorite": false}, {"pk": 4686320798, "username": "imalexstokes", "full_name": "Alex Stokes", "is_private": false, "profile_pic_url": "https://scontent-tpe1-1.cdninstagram.com/v/t51.2885-19/s150x150/62116337_2060887707551797_7629197789964009472_n.jpg?_nc_ht=scontent-tpe1-1.cdninstagram.com&_nc_ohc=MZkg8GLEmtUAX-h9EWz&oh=0c24bc515fa770c5ed3081fa08626817&oe=5E8F2B73", "profile_pic_id": "2070000915238176310_4686320798", "is_verified": true, "has_anonymous_profile_picture": false, "can_see_primary_country_in_settings": false, "latest_reel_media": 0, "is_favorite": false}, {"pk": 20194944, "username": "tichinaarnold", "full_name": "TICHINA ARNOLD", "is_private": false, "profile_pic_url": "https://scontent-tpe1-1.cdninstagram.com/v/t51.2885-19/s150x150/77094667_576601142906692_5186492018615910400_n.jpg?_nc_ht=scontent-tpe1-1.cdninstagram.com&_nc_ohc=Qgo3BTlab_QAX9cnz1H&oh=a83daa71784ff29fd20819c0e6a33e6d&oe=5EAB32D5", "profile_pic_id": "2181308713223437128_20194944", "is_verified": true, "has_anonymous_profile_picture": false, "can_see_primary_country_in_settings": false, "latest_reel_media": 0, "is_favorite": false}, {"pk": 4686316577, "username": "imalanstokes", "full_name": "Alan Stokes", "is_private": false, "profile_pic_url": "https://scontent-tpe1-1.cdninstagram.com/v/t51.2885-19/s150x150/51694808_2268134753409769_6256944898394554368_n.jpg?_nc_ht=scontent-tpe1-1.cdninstagram.com&_nc_ohc=C6_RjNiMdrkAX8mELWs&oh=6d318852c369c55f9c29a74657bec62b&oe=5EAA439A", "profile_pic_id": "1990607578656227159_4686316577", "is_verified": true, "has_anonymous_profile_picture": false, "can_see_primary_country_in_settings": false, "latest_reel_media": 1578239514, "is_favorite": false}, {"pk": 1722857943, "username": "stxentertainment", "full_name": "STX Entertainment", "is_private": false, "profile_pic_url": "https://scontent-tpe1-1.cdninstagram.com/v/t51.2885-19/s150x150/13151379_1652576681717103_1928703578_a.jpg?_nc_ht=scontent-tpe1-1.cdninstagram.com&_nc_ohc=jE-dq66nTrYAX9HbZD8&oh=5d5ecd969b9bc1758e56716d87865f1b&oe=5E99E9EA", "profile_pic_id": "1252628277637284505_1722857943", "is_verified": true, "has_anonymous_profile_picture": false, "can_see_primary_country_in_settings": false, "latest_reel_media": 1578277517, "is_favorite": false}, {"pk": 196613241, "username": "j_calloway6", "full_name": "Jordan Calloway", "is_private": false, "profile_pic_url": "https://scontent-tpe1-1.cdninstagram.com/v/t51.2885-19/s150x150/26066608_160411264578264_5404092774276399104_n.jpg?_nc_ht=scontent-tpe1-1.cdninstagram.com&_nc_ohc=kfSuMtpDRLkAX8LZcBI&oh=c5dc6fd3aab460012c1e04c1be637546&oe=5EA016BF", "profile_pic_id": "1679634103152253718_196613241", "is_verified": true, "has_anonymous_profile_picture": false, "can_see_primary_country_in_settings": false, "latest_reel_media": 1578262858, "is_favorite": false}, {"pk": 1682487928, "username": "buildseriesnyc", "full_name": "BUILD Series", "is_private": false, "profile_pic_url": "https://scontent-tpe1-1.cdninstagram.com/v/t51.2885-19/s150x150/72960156_543785846190230_4813304328901099520_n.jpg?_nc_ht=scontent-tpe1-1.cdninstagram.com&_nc_ohc=dgbKrq2dZHcAX8vE8TJ&oh=59f28626076a570058e79a6093e10a81&oe=5EAFFB01", "profile_pic_id": "2157511908194660760_1682487928", "is_verified": true, "has_anonymous_profile_picture": false, "can_see_primary_country_in_settings": false, "latest_reel_media": 0, "is_favorite": false}]