[{"pk": 2995814201, "username": "helenswines", "full_name": "helen\u2019s wines", "is_private": false, "profile_pic_url": "https://scontent-tpe1-1.cdninstagram.com/vp/2d2ec1cf2f8f40cbe2fe7ffec00b53aa/5DF76CEF/t51.2885-19/s150x150/1171920_239784299695588_1353720658_a.jpg?_nc_ht=scontent-tpe1-1.cdninstagram.com", "is_verified": true, "has_anonymous_profile_picture": false, "latest_reel_media": 1567290783, "is_favorite": false}, {"pk": 272220114, "username": "leandramcohen", "full_name": "Leandra (Medine) Cohen", "is_private": false, "profile_pic_url": "https://scontent-tpe1-1.cdninstagram.com/vp/9985da66bc401416e5b44f74879a8459/5DFF0F9F/t51.2885-19/s150x150/22344266_2035595253337469_3094193636603068416_n.jpg?_nc_ht=scontent-tpe1-1.cdninstagram.com", "profile_pic_id": "1620313703553457760_272220114", "is_verified": true, "has_anonymous_profile_picture": false, "latest_reel_media": 0, "is_favorite": false}, {"pk": 26252444, "username": "chrissyteigen", "full_name": "chrissy teigen", "is_private": false, "profile_pic_url": "https://scontent-tpe1-1.cdninstagram.com/vp/c5a7b6c2511fee09986c215072f1860f/5E09D3A8/t51.2885-19/s150x150/14134625_577960212411719_1003313256_a.jpg?_nc_ht=scontent-tpe1-1.cdninstagram.com", "profile_pic_id": "1329312142125926697_26252444", "is_verified": true, "has_anonymous_profile_picture": false, "latest_reel_media": 1567301524, "is_favorite": false}, {"pk": 2243375, "username": "alliwebb", "full_name": "Alli Webb", "is_private": false, "profile_pic_url": "https://scontent-tpe1-1.cdninstagram.com/vp/fc54a6de2af4845717f01bc64130ab72/5DF6E066/t51.2885-19/s150x150/67117876_390510611652418_856327779157803008_n.jpg?_nc_ht=scontent-tpe1-1.cdninstagram.com", "profile_pic_id": "2113899606403515095_2243375", "is_verified": true, "has_anonymous_profile_picture": false, "latest_reel_media": 1567360651, "is_favorite": false}, {"pk": 2746396, "username": "sophieandlili", "full_name": "Sophie & Lili \u2122", "is_private": false, "profile_pic_url": "https://scontent-tpe1-1.cdninstagram.com/vp/7b04ad97bbf3299c5d6fffd0c00331a2/5E08A979/t51.2885-19/s150x150/12292704_1011291482263479_1355968637_a.jpg?_nc_ht=scontent-tpe1-1.cdninstagram.com", "is_verified": false, "has_anonymous_profile_picture": false, "latest_reel_media": 1567334151, "is_favorite": false}, {"pk": 8047320, "username": "rachellehruska", "full_name": "Rachelle Hruska MacPherson", "is_private": false, "profile_pic_url": "https://scontent-tpe1-1.cdninstagram.com/vp/9c2e1430ebcc136c6f59d4bc3611ee67/5DEF40E0/t51.2885-19/s150x150/28433030_2135328623148892_7176776839925334016_n.jpg?_nc_ht=scontent-tpe1-1.cdninstagram.com", "profile_pic_id": "1733683644897399590_8047320", "is_verified": false, "has_anonymous_profile_picture": false, "latest_reel_media": 1567358515, "is_favorite": false}, {"pk": 1834271085, "username": "hillaryclinton", "full_name": "Hillary Clinton", "is_private": false, "profile_pic_url": "https://scontent-tpe1-1.cdninstagram.com/vp/75a9dbe3562768ac8c69a5edd0685c61/5DF1013D/t51.2885-19/s150x150/43280843_992191047645523_228685589510094848_n.jpg?_nc_ht=scontent-tpe1-1.cdninstagram.com", "profile_pic_id": "1890931861707072481_1834271085", "is_verified": true, "has_anonymous_profile_picture": false, "latest_reel_media": 0, "is_favorite": false}, {"pk": 499828240, "username": "cledepeaubeauteus", "full_name": "Cl\u00e9 de Peau Beaut\u00e9 US", "is_private": false, "profile_pic_url": "https://scontent-tpe1-1.cdninstagram.com/vp/14d48e0fa6481d0444155d5b98a53e54/5E0FB408/t51.2885-19/s150x150/40357132_230824071114299_4502246502218858496_n.jpg?_nc_ht=scontent-tpe1-1.cdninstagram.com", "profile_pic_id": "1862602958634775698_499828240", "is_verified": true, "has_anonymous_profile_picture": false, "latest_reel_media": 0, "is_favorite": false}, {"pk": 4534106594, "username": "dissentpins", "full_name": "Dissent Pins", "is_private": false, "profile_pic_url": "https://scontent-tpe1-1.cdninstagram.com/vp/7def09f7c0756bb2476bc439145e3c6c/5E1591D6/t51.2885-19/s150x150/41172570_1355600904577363_3600605220360421376_n.jpg?_nc_ht=scontent-tpe1-1.cdninstagram.com", "profile_pic_id": "1879373164803664689_4534106594", "is_verified": false, "has_anonymous_profile_picture": false, "latest_reel_media": 0, "is_favorite": false}, {"pk": 3175581679, "username": "linguafrancanyc", "full_name": "Lingua Franca", "is_private": false, "profile_pic_url": "https://scontent-tpe1-1.cdninstagram.com/vp/42c3fe66a8dcda31d22b731a4915e82d/5DFA8F2B/t51.2885-19/s150x150/14533496_1617393398560762_4069925681297883136_a.jpg?_nc_ht=scontent-tpe1-1.cdninstagram.com", "profile_pic_id": "1350187966983390160_3175581679", "is_verified": true, "has_anonymous_profile_picture": false, "latest_reel_media": 1567350252, "is_favorite": false}, {"pk": 2680730803, "username": "cledepeaubeaute", "full_name": "Cl\u00e9 de Peau Beaut\u00e9", "is_private": false, "profile_pic_url": "https://scontent-tpe1-1.cdninstagram.com/vp/838a6ab2ae3f07ca9c69c560352a0310/5DF49B73/t51.2885-19/s150x150/23507220_150066192279001_970222847194562560_n.jpg?_nc_ht=scontent-tpe1-1.cdninstagram.com", "profile_pic_id": "1644811196150237375_2680730803", "is_verified": true, "has_anonymous_profile_picture": false, "latest_reel_media": 1567323425, "is_favorite": false}, {"pk": 194077182, "username": "soludos", "full_name": "Soludos", "is_private": false, "profile_pic_url": "https://scontent-tpe1-1.cdninstagram.com/vp/3eda412ed3fd99926e0669181e886af3/5E0FCDDC/t51.2885-19/s150x150/18646623_1921241361450237_8917829777109286912_a.jpg?_nc_ht=scontent-tpe1-1.cdninstagram.com", "profile_pic_id": "1523093296421915030_194077182", "is_verified": true, "has_anonymous_profile_picture": false, "latest_reel_media": 1567357357, "is_favorite": false}, {"pk": 175908878, "username": "shopclarev", "full_name": "Clare V.", "is_private": false, "profile_pic_url": "https://scontent-tpe1-1.cdninstagram.com/vp/b66d8b01ef2c5b5d4ee27264162c4dd3/5DF181EE/t51.2885-19/s150x150/54217456_2322368987825617_5832554163354992640_n.jpg?_nc_ht=scontent-tpe1-1.cdninstagram.com", "profile_pic_id": "2013310233141386589_175908878", "is_verified": true, "has_anonymous_profile_picture": false, "latest_reel_media": 0, "is_favorite": false}, {"pk": 10085244, "username": "dvf", "full_name": "DVF - Diane von Furstenberg", "is_private": false, "profile_pic_url": "https://scontent-tpe1-1.cdninstagram.com/vp/497470c7fc995b48133066b16b5022f1/5DF2DF69/t51.2885-19/s150x150/57650918_300889034155486_7431926991416197120_n.jpg?_nc_ht=scontent-tpe1-1.cdninstagram.com", "profile_pic_id": "2035654212819181959_10085244", "is_verified": true, "has_anonymous_profile_picture": false, "latest_reel_media": 1567354751, "is_favorite": false}, {"pk": 7177069, "username": "catbirdnyc", "full_name": "Catbird", "is_private": false, "profile_pic_url": "https://scontent-tpe1-1.cdninstagram.com/vp/2395e75c259bf0c90c310d6899e2aa32/5E1287B1/t51.2885-19/s150x150/40850738_324819948074825_4261456376313675776_n.jpg?_nc_ht=scontent-tpe1-1.cdninstagram.com", "profile_pic_id": "1869001693842417646_7177069", "is_verified": true, "has_anonymous_profile_picture": false, "latest_reel_media": 1567353688, "is_favorite": false}, {"pk": 25527800, "username": "elizabethchambers", "full_name": "Elizabeth Chambers Hammer", "is_private": false, "profile_pic_url": "https://scontent-tpe1-1.cdninstagram.com/vp/3f916daf1348cab4ae5257f9a02045a5/5E13A2F8/t51.2885-19/s150x150/59422780_364222777537204_164529807583870976_n.jpg?_nc_ht=scontent-tpe1-1.cdninstagram.com", "profile_pic_id": "2044735172406369670_25527800", "is_verified": true, "has_anonymous_profile_picture": false, "latest_reel_media": 1567305015, "is_favorite": false}, {"pk": 173761491, "username": "americanfilminstitute", "full_name": "American Film Institute", "is_private": false, "profile_pic_url": "https://scontent-tpe1-1.cdninstagram.com/vp/929c849763e78c307fd122ce52ec3a98/5E010EA3/t51.2885-19/s150x150/26871064_386639148461797_7372028411138539520_n.jpg?_nc_ht=scontent-tpe1-1.cdninstagram.com", "profile_pic_id": "1710363837688769498_173761491", "is_verified": true, "has_anonymous_profile_picture": false, "latest_reel_media": 0, "is_favorite": false}, {"pk": 51053796, "username": "iiswhoiis", "full_name": "Kesha", "is_private": false, "profile_pic_url": "https://scontent-tpe1-1.cdninstagram.com/vp/c5e4ee6f807a82cb89a814c6c45506f2/5E063267/t51.2885-19/s150x150/67403709_460994338066277_1669230204842672128_n.jpg?_nc_ht=scontent-tpe1-1.cdninstagram.com", "profile_pic_id": "2096533217897591197_51053796", "is_verified": true, "has_anonymous_profile_picture": false, "latest_reel_media": 0, "is_favorite": false}, {"pk": 104739566, "username": "participant", "full_name": "Participant Media", "is_private": false, "profile_pic_url": "https://scontent-tpe1-1.cdninstagram.com/vp/d22d2625cc0728c4578ef94f1e7203e9/5DFF892C/t51.2885-19/s150x150/42003246_1050462818466420_1267161883719237632_n.jpg?_nc_ht=scontent-tpe1-1.cdninstagram.com", "profile_pic_id": "1883779048540650402_104739566", "is_verified": true, "has_anonymous_profile_picture": false, "latest_reel_media": 0, "is_favorite": false}, {"pk": 509247209, "username": "focusfeatures", "full_name": "Focus Features", "is_private": false, "profile_pic_url": "https://scontent-tpe1-1.cdninstagram.com/vp/7c944b37aa4395badf6c575475f9d14b/5E0CBF37/t51.2885-19/s150x150/40465551_712823255734965_2690065882956169216_n.jpg?_nc_ht=scontent-tpe1-1.cdninstagram.com", "profile_pic_id": "1868438692735465133_509247209", "is_verified": true, "has_anonymous_profile_picture": false, "latest_reel_media": 0, "is_favorite": false}, {"pk": 20743323, "username": "caileespaeny", "full_name": "Cailee Spaeny", "is_private": false, "profile_pic_url": "https://scontent-tpe1-1.cdninstagram.com/vp/e9761b801e050bf7156882320372ac20/5E11989D/t51.2885-19/s150x150/67823767_501612763933953_3890088309623357440_n.jpg?_nc_ht=scontent-tpe1-1.cdninstagram.com", "profile_pic_id": "2007750716852290396_20743323", "is_verified": true, "has_anonymous_profile_picture": false, "latest_reel_media": 1567285882, "is_favorite": false}, {"pk": 2205179321, "username": "justintheroux", "full_name": "", "is_private": false, "profile_pic_url": "https://scontent-tpe1-1.cdninstagram.com/vp/5291790042754dccb44a3c7e0a92006a/5DF9B248/t51.2885-19/s150x150/12362145_1129235200435060_2002300323_a.jpg?_nc_ht=scontent-tpe1-1.cdninstagram.com", "is_verified": true, "has_anonymous_profile_picture": false, "latest_reel_media": 1567303262, "is_favorite": false}, {"pk": 402099325, "username": "armiehammer", "full_name": "Armie Hammer", "is_private": false, "profile_pic_url": "https://scontent-tpe1-1.cdninstagram.com/vp/6d408afe566e8ffe178ce82bddd4e991/5E13CDDA/t51.2885-19/s150x150/20184840_320934591695020_4549105372807299072_a.jpg?_nc_ht=scontent-tpe1-1.cdninstagram.com", "profile_pic_id": "1562810829995715352_402099325", "is_verified": true, "has_anonymous_profile_picture": false, "latest_reel_media": 1567351594, "is_favorite": false}, {"pk": 1799229640, "username": "mimi.leder", "full_name": "Mimi Leder", "is_private": false, "profile_pic_url": "https://scontent-tpe1-1.cdninstagram.com/vp/77ca030c86e09e4edaff46f432de2e9c/5E040CFB/t51.2885-19/11055781_1403181969998688_1757289576_a.jpg?_nc_ht=scontent-tpe1-1.cdninstagram.com", "is_verified": true, "has_anonymous_profile_picture": false, "latest_reel_media": 0, "is_favorite": false}]